MANIFEST.in
README.rst
requirements.txt
setup.cfg
setup.py
djmicrosip_clasificadores/__init__.py
djmicrosip_clasificadores/__init__.pyc
djmicrosip_clasificadores/config.py
djmicrosip_clasificadores/config.pyc
djmicrosip_clasificadores/forms.py
djmicrosip_clasificadores/forms.pyc
djmicrosip_clasificadores/models.py
djmicrosip_clasificadores/models.pyc
djmicrosip_clasificadores/send_mail.py
djmicrosip_clasificadores/send_mail.pyc
djmicrosip_clasificadores/storage.py
djmicrosip_clasificadores/storage.pyc
djmicrosip_clasificadores/urls.py
djmicrosip_clasificadores/urls.pyc
djmicrosip_clasificadores/views.py
djmicrosip_clasificadores/views.pyc
djmicrosip_clasificadores.egg-info/PKG-INFO
djmicrosip_clasificadores.egg-info/SOURCES.txt
djmicrosip_clasificadores.egg-info/dependency_links.txt
djmicrosip_clasificadores.egg-info/requires.txt
djmicrosip_clasificadores.egg-info/top_level.txt
djmicrosip_clasificadores/__pycache__/__init__.cpython-38.pyc
djmicrosip_clasificadores/__pycache__/config.cpython-38.pyc
djmicrosip_clasificadores/__pycache__/forms.cpython-38.pyc
djmicrosip_clasificadores/__pycache__/models.cpython-38.pyc
djmicrosip_clasificadores/__pycache__/send_mail.cpython-38.pyc
djmicrosip_clasificadores/__pycache__/storage.cpython-38.pyc
djmicrosip_clasificadores/__pycache__/urls.cpython-38.pyc
djmicrosip_clasificadores/__pycache__/views.cpython-38.pyc
djmicrosip_clasificadores/static/djmicrosip_clasificadores/js/bootstrap-input-spinner.js
djmicrosip_clasificadores/templates/djmicrosip_clasificadores/asignar_compatibilidad_articulos.html
djmicrosip_clasificadores/templates/djmicrosip_clasificadores/base.html
djmicrosip_clasificadores/templates/djmicrosip_clasificadores/cambiar_contraseña.html
djmicrosip_clasificadores/templates/djmicrosip_clasificadores/compatibilidad.html
djmicrosip_clasificadores/templates/djmicrosip_clasificadores/index.html
djmicrosip_clasificadores/templates/djmicrosip_clasificadores/preferencias.html
djmicrosip_clasificadores/templates/djmicrosip_clasificadores/recuperar_contrasena.html
djmicrosip_clasificadores/templates/djmicrosip_clasificadores/usuarios_clientes.html
djmicrosip_clasificadores/templates/djmicrosip_clasificadores/view_pedido.html